odoo/addons/pos_product_default_code/README.rst
odoo/addons/pos_product_default_code/__init__.py
odoo/addons/pos_product_default_code/__manifest__.py
odoo/addons/pos_product_default_code/i18n/it.po
odoo/addons/pos_product_default_code/i18n/pos_product_default_code.pot
odoo/addons/pos_product_default_code/readme/CONTRIBUTORS.rst
odoo/addons/pos_product_default_code/readme/DESCRIPTION.rst
odoo/addons/pos_product_default_code/static/description/icon.png
odoo/addons/pos_product_default_code/static/description/index.html
odoo/addons/pos_product_default_code/static/src/css/pos.css
odoo/addons/pos_product_default_code/static/src/xml/pos.xml
odoo/addons/pos_product_default_code/views/templates.xml
odoo12_addon_pos_product_default_code-12.0.1.0.0.99.dev6.dist-info/METADATA
odoo12_addon_pos_product_default_code-12.0.1.0.0.99.dev6.dist-info/WHEEL
odoo12_addon_pos_product_default_code-12.0.1.0.0.99.dev6.dist-info/top_level.txt
odoo12_addon_pos_product_default_code-12.0.1.0.0.99.dev6.dist-info/RECORD
